skelmis/docx/__init__.py
skelmis/docx/api.py
skelmis/docx/blkcntnr.py
skelmis/docx/document.py
skelmis/docx/exceptions.py
skelmis/docx/package.py
skelmis/docx/py.typed
skelmis/docx/section.py
skelmis/docx/settings.py
skelmis/docx/shape.py
skelmis/docx/shared.py
skelmis/docx/table.py
skelmis/docx/types.py
skelmis/docx/dml/__init__.py
skelmis/docx/dml/color.py
skelmis/docx/drawing/__init__.py
skelmis/docx/enum/__init__.py
skelmis/docx/enum/base.py
skelmis/docx/enum/dml.py
skelmis/docx/enum/section.py
skelmis/docx/enum/shape.py
skelmis/docx/enum/style.py
skelmis/docx/enum/table.py
skelmis/docx/enum/text.py
skelmis/docx/image/__init__.py
skelmis/docx/image/bmp.py
skelmis/docx/image/constants.py
skelmis/docx/image/exceptions.py
skelmis/docx/image/gif.py
skelmis/docx/image/helpers.py
skelmis/docx/image/image.py
skelmis/docx/image/jpeg.py
skelmis/docx/image/png.py
skelmis/docx/image/tiff.py
skelmis/docx/opc/__init__.py
skelmis/docx/opc/constants.py
skelmis/docx/opc/coreprops.py
skelmis/docx/opc/exceptions.py
skelmis/docx/opc/oxml.py
skelmis/docx/opc/package.py
skelmis/docx/opc/packuri.py
skelmis/docx/opc/part.py
skelmis/docx/opc/phys_pkg.py
skelmis/docx/opc/pkgreader.py
skelmis/docx/opc/pkgwriter.py
skelmis/docx/opc/rel.py
skelmis/docx/opc/shared.py
skelmis/docx/opc/spec.py
skelmis/docx/opc/parts/__init__.py
skelmis/docx/opc/parts/coreprops.py
skelmis/docx/oxml/__init__.py
skelmis/docx/oxml/coreprops.py
skelmis/docx/oxml/document.py
skelmis/docx/oxml/drawing.py
skelmis/docx/oxml/exceptions.py
skelmis/docx/oxml/ns.py
skelmis/docx/oxml/numbering.py
skelmis/docx/oxml/parser.py
skelmis/docx/oxml/section.py
skelmis/docx/oxml/settings.py
skelmis/docx/oxml/shape.py
skelmis/docx/oxml/shared.py
skelmis/docx/oxml/simpletypes.py
skelmis/docx/oxml/styles.py
skelmis/docx/oxml/table.py
skelmis/docx/oxml/xmlchemy.py
skelmis/docx/oxml/text/__init__.py
skelmis/docx/oxml/text/font.py
skelmis/docx/oxml/text/hyperlink.py
skelmis/docx/oxml/text/pagebreak.py
skelmis/docx/oxml/text/paragraph.py
skelmis_docx-2.6.0.dist-info/METADATA
skelmis_docx-2.6.0.dist-info/WHEEL
skelmis_docx-2.6.0.dist-info/licenses/LICENSE
skelmis_docx-2.6.0.dist-info/RECORD
