Metadata-Version: 2.4
Name: skelmis-docx
Version: 2.6.0
Summary: Create, read, and update Microsoft Word .docx files.
Project-URL: Homepage, https://github.com/skelmis/python-docx
Project-URL: Documentation, https://skelmis-docx.readthedocs.io/en/latest/
Project-URL: Issue tracker, https://github.com/Skelmis/python-docx/issues
Project-URL: Changelog, https://github.com/Skelmis/python-docx/blob/master/HISTORY.rst
Author-email: Skelmis <skelmis.craft@gmail.com>
License-Expression: MIT
License-File: LICENSE
Keywords: Docx
Classifier: Development Status :: 5 - Production/Stable
Classifier: Intended Audience :: Developers
Classifier: Programming Language :: Python :: 3
Classifier: Programming Language :: Python :: 3.10
Classifier: Programming Language :: Python :: 3.11
Classifier: Programming Language :: Python :: 3.12
Classifier: Programming Language :: Python :: 3.13
Requires-Python: >=3.10
Requires-Dist: lxml>=5.0.0
Requires-Dist: pywin32>=307; sys_platform == 'windows'
Requires-Dist: typing-extensions<5,>=4.12.2
